README.md
setup.py
event_mill/__init__.py
event_mill/exceptions.py
event_mill.egg-info/PKG-INFO
event_mill.egg-info/SOURCES.txt
event_mill.egg-info/dependency_links.txt
event_mill.egg-info/not-zip-safe
event_mill.egg-info/requires.txt
event_mill.egg-info/top_level.txt
event_mill/event/__init__.py
event_mill/event/declarations.py
event_mill/event_source/__init__.py
event_mill/event_source/declarations.py
event_mill/projection/__init__.py
event_mill/projection/declarations.py
event_mill/projection/definitions.py
event_mill/reactor/__init__.py
event_mill/reactor/declarations.py
event_mill/reactor/definitions.py
test/test.py