Metadata-Version: 1.1
Name: event-mill
Version: 0.1.0
Summary: A framework for projections from event stores
Home-page: https://github.com/fcracker79/event_mill
Author: UNKNOWN
Author-email: UNKNOWN
License: MIT
Keywords: event DDD domain projection store
Platform: UNKNOWN
Classifier: Development Status :: 4 - Beta
Classifier: Intended Audience :: Developers
Classifier: Topic :: Software Development
Classifier: License :: OSI Approved :: MIT License
Classifier: Programming Language :: Python :: 3.2
Classifier: Programming Language :: Python :: 3.3
Classifier: Programming Language :: Python :: 3.4
Classifier: Programming Language :: Python :: 3.5
Classifier: Programming Language :: Python :: 3.6
